asyncmcp/__init__.py
asyncmcp/py.typed
asyncmcp/common/__init__.py
asyncmcp/common/aws_queue_utils.py
asyncmcp/common/base_client.py
asyncmcp/common/client_state.py
asyncmcp/common/outgoing_event.py
asyncmcp/common/protocols.py
asyncmcp/common/server.py
asyncmcp/common/utils.py
asyncmcp/proxy/README.md
asyncmcp/proxy/__init__.py
asyncmcp/proxy/client.py
asyncmcp/proxy/interceptor.py
asyncmcp/proxy/message_handler.py
asyncmcp/proxy/server.py
asyncmcp/proxy/session.py
asyncmcp/proxy/session_manager.py
asyncmcp/proxy/session_resolver.py
asyncmcp/proxy/sse_handler.py
asyncmcp/proxy/utils.py
asyncmcp/sns_sqs/__init__.py
asyncmcp/sns_sqs/client.py
asyncmcp/sns_sqs/manager.py
asyncmcp/sns_sqs/server.py
asyncmcp/sns_sqs/utils.py
asyncmcp/sqs/__init__.py
asyncmcp/sqs/client.py
asyncmcp/sqs/manager.py
asyncmcp/sqs/server.py
asyncmcp/sqs/utils.py
asyncmcp/streamable_http_webhook/__init__.py
asyncmcp/streamable_http_webhook/client.py
asyncmcp/streamable_http_webhook/manager.py
asyncmcp/streamable_http_webhook/routing.py
asyncmcp/streamable_http_webhook/server.py
asyncmcp/streamable_http_webhook/utils.py
asyncmcp/webhook/__init__.py
asyncmcp/webhook/client.py
asyncmcp/webhook/manager.py
asyncmcp/webhook/server.py
asyncmcp/webhook/utils.py
asyncmcp-0.2.1.dist-info/METADATA
asyncmcp-0.2.1.dist-info/WHEEL
asyncmcp-0.2.1.dist-info/licenses/LICENSE
asyncmcp-0.2.1.dist-info/RECORD
